graphene_django_extras/__init__.py
graphene_django_extras/base_types.py
graphene_django_extras/converter.py
graphene_django_extras/directives/__init__.py
graphene_django_extras/directives/base.py
graphene_django_extras/directives/date.py
graphene_django_extras/directives/list.py
graphene_django_extras/directives/numbers.py
graphene_django_extras/directives/string.py
graphene_django_extras/fields.py
graphene_django_extras/filters/__init__.py
graphene_django_extras/filters/filter.py
graphene_django_extras/filters/lookups.py
graphene_django_extras/middleware.py
graphene_django_extras/mutation.py
graphene_django_extras/paginations/__init__.py
graphene_django_extras/paginations/fields.py
graphene_django_extras/paginations/pagination.py
graphene_django_extras/paginations/utils.py
graphene_django_extras/registry.py
graphene_django_extras/settings.py
graphene_django_extras/types.py
graphene_django_extras/utils.py
graphene_django_extras/views.py
graphene_django_extras-1.1.0.dist-info/METADATA
graphene_django_extras-1.1.0.dist-info/WHEEL
graphene_django_extras-1.1.0.dist-info/licenses/LICENSE
graphene_django_extras-1.1.0.dist-info/RECORD
