Metadata-Version: 2.4
Name: graphene-django-extras
Version: 1.1.0
Summary: This library adds extra functionalities to graphene-django to facilitate GraphQL use without Relay, allow paginations and filtering integration, and add extra directives.
License: MIT
License-File: LICENSE
Keywords: api,graphql,protocol,graphene,django
Author: Ernesto Perez Amigo
Author-email: eamigop86@gmail.com
Requires-Python: >=3.12,<4.0
Classifier: Framework :: Django
Classifier: Framework :: Django :: 4.0
Classifier: Framework :: Django :: 4.2
Classifier: Framework :: Django :: 5.0
Classifier: Framework :: Django :: 5.1
Classifier: Framework :: Django :: 5.2
Classifier: Framework :: Django :: 6.0
Classifier: Intended Audience :: Developers
Classifier: License :: OSI Approved :: MIT License
Classifier: Programming Language :: Python :: 3
Classifier: Programming Language :: Python :: 3.12
Classifier: Programming Language :: Python :: 3.13
Classifier: Programming Language :: Python :: 3.14
Classifier: Programming Language :: Python :: 3 :: Only
Classifier: Programming Language :: Python :: Implementation :: PyPy
Classifier: Topic :: Software Development :: Libraries
Requires-Dist: django (>=4.0,<7.0)
Requires-Dist: django-filter (>=22.1)
Requires-Dist: djangorestframework (>=3,<4)
Requires-Dist: graphene-django (>=3.2,<4.0)
Requires-Dist: python-dateutil (>=2.8.2,<3.0)
Project-URL: Documentation, https://github.com/eamigo86/graphene-django-extras
Project-URL: Homepage, https://github.com/eamigo86/graphene-django-extras
Project-URL: Repository, https://github.com/eamigo86/graphene-django-extras
